README.rst
nbank/__init__.py
nbank/admin.py
nbank/archive.py
nbank/core.py
nbank/registry.py
nbank/script.py
nbank/tape_archive.py
nbank/types.py
nbank/util.py
neurobank-0.11.1.dist-info/METADATA
neurobank-0.11.1.dist-info/WHEEL
neurobank-0.11.1.dist-info/entry_points.txt
neurobank-0.11.1.dist-info/licenses/COPYING
neurobank-0.11.1.dist-info/RECORD
