Metadata-Version: 2.4
Name: neurobank
Version: 0.11.1
Summary: Simple data management system for neuroscience
Project-URL: Homepage, https://github.com/melizalab/neurobank
Author-email: Dan Meliza <dan@meliza.org>
Maintainer-email: Dan Meliza <dan@meliza.org>
License: BSD 3-Clause License
License-File: COPYING
Classifier: Development Status :: 4 - Beta
Classifier: Intended Audience :: Science/Research
Classifier: License :: OSI Approved :: BSD License
Classifier: Natural Language :: English
Classifier: Operating System :: MacOS :: MacOS X
Classifier: Operating System :: POSIX :: Linux
Classifier: Operating System :: Unix
Classifier: Programming Language :: Python
Classifier: Programming Language :: Python :: 3.8
Classifier: Programming Language :: Python :: 3.9
Classifier: Programming Language :: Python :: 3.10
Classifier: Programming Language :: Python :: 3.11
Classifier: Programming Language :: Python :: 3.12
Classifier: Programming Language :: Python :: Implementation :: CPython
Classifier: Programming Language :: Python :: Implementation :: PyPy
Classifier: Topic :: Scientific/Engineering
Requires-Python: >=3.8
Requires-Dist: httpx>=0.24
